<annotation>
	<folder>invoices</folder>
	<filename>invoice (1).jpg</filename>
	<path>C:\Users\FRIENDS INFOTECH\Desktop\invoices\invoice (1).jpg</path>
	<source>
		<database>Unknown</database>
	</source>
	<size>
		<width>600</width>
		<height>800</height>
		<depth>3</depth>
	</size>
	<segmented>0</segmented>
	<object>
		<name>Amount</name>
		<pose>Unspecified</pose>
		<truncated>0</truncated>
		<difficult>0</difficult>
		<bndbox>
			<xmin>379</xmin>
			<ymin>398</ymin>
			<xmax>569</xmax>
			<ymax>432</ymax>
		</bndbox>
	</object>
	<object>
		<name>InvoiceNumber</name>
		<pose>Unspecified</pose>
		<truncated>0</truncated>
		<difficult>0</difficult>
		<bndbox>
			<xmin>364</xmin>
			<ymin>92</ymin>
			<xmax>486</xmax>
			<ymax>111</ymax>
		</bndbox>
	</object>
	<object>
		<name>InvoiceDate</name>
		<pose>Unspecified</pose>
		<truncated>0</truncated>
		<difficult>0</difficult>
		<bndbox>
			<xmin>366</xmin>
			<ymin>111</ymin>
			<xmax>488</xmax>
			<ymax>126</ymax>
		</bndbox>
	</object>
	<object>
		<name>Items</name>
		<pose>Unspecified</pose>
		<truncated>0</truncated>
		<difficult>0</difficult>
		<bndbox>
			<xmin>22</xmin>
			<ymin>270</ymin>
			<xmax>568</xmax>
			<ymax>353</ymax>
		</bndbox>
	</object>
	<object>
		<name>Client Info</name>
		<pose>Unspecified</pose>
		<truncated>0</truncated>
		<difficult>0</difficult>
		<bndbox>
			<xmin>22</xmin>
			<ymin>198</ymin>
			<xmax>88</xmax>
			<ymax>248</ymax>
		</bndbox>
	</object>
</annotation>
